{"nodes": [{"id": "canvasimage", "label": "CanvasImage.tsx", "file_type": "code", "source_file": "components/drawing/CanvasImage.tsx", "source_location": "L1"}, {"id": "canvasimage_canvasimage", "label": "CanvasImage()", "file_type": "code", "source_file": "components/drawing/CanvasImage.tsx", "source_location": "L40"}], "edges": [{"source": "canvasimage", "target": "react", "relation": "imports_from", "confidence": "EXTRACTED", "source_file": "components/drawing/CanvasImage.tsx", "source_location": "L8", "weight": 1.0}, {"source": "canvasimage", "target": "perspectivewarp", "relation": "imports_from", "confidence": "EXTRACTED", "source_file": "components/drawing/CanvasImage.tsx", "source_location": "L9", "weight": 1.0}, {"source": "canvasimage", "target": "canvasimage_canvasimage", "relation": "contains", "confidence": "EXTRACTED", "source_file": "components/drawing/CanvasImage.tsx", "source_location": "L40", "weight": 1.0}]}