{"nodes": [{"id": "gamma", "label": "gamma.js", "file_type": "code", "source_file": "node_modules/culori/src/easing/gamma.js", "source_location": "L1"}, {"id": "gamma_gamma", "label": "gamma()", "file_type": "code", "source_file": "node_modules/culori/src/easing/gamma.js", "source_location": "L1"}], "edges": [{"source": "gamma", "target": "gamma_gamma", "relation": "contains", "confidence": "EXTRACTED", "source_file": "node_modules/culori/src/easing/gamma.js", "source_location": "L1", "weight": 1.0}]}