{"nodes": [{"id": "index", "label": "index.js", "file_type": "code", "source_file": "node_modules/next/dist/esm/build/output/index.js", "source_location": "L1"}, {"id": "index_formatampmessages", "label": "formatAmpMessages()", "file_type": "code", "source_file": "node_modules/next/dist/esm/build/output/index.js", "source_location": "L8"}, {"id": "index_ampvalidation", "label": "ampValidation()", "file_type": "code", "source_file": "node_modules/next/dist/esm/build/output/index.js", "source_location": "L144"}, {"id": "index_watchcompilers", "label": "watchCompilers()", "file_type": "code", "source_file": "node_modules/next/dist/esm/build/output/index.js", "source_location": "L165"}, {"id": "index_reporttrigger", "label": "reportTrigger()", "file_type": "code", "source_file": "node_modules/next/dist/esm/build/output/index.js", "source_location": "L243"}], "edges": [{"source": "index", "target": "picocolors", "relation": "imports_from", "confidence": "EXTRACTED", "source_file": "node_modules/next/dist/esm/build/output/index.js", "source_location": "L1", "weight": 1.0}, {"source": "index", "target": "strip_ansi", "relation": "imports_from", "confidence": "EXTRACTED", "source_file": "node_modules/next/dist/esm/build/output/index.js", "source_location": "L2", "weight": 1.0}, {"source": "index", "target": "text_table", "relation": "imports_from", "confidence": "EXTRACTED", "source_file": "node_modules/next/dist/esm/build/output/index.js", "source_location": "L3", "weight": 1.0}, {"source": "index", "target": "unistore", "relation": "imports_from", "confidence": "EXTRACTED", "source_file": "node_modules/next/dist/esm/build/output/index.js", "source_location": "L4", "weight": 1.0}, {"source": "index", "target": "format_webpack_messages", "relation": "imports_from", "confidence": "EXTRACTED", "source_file": "node_modules/next/dist/esm/build/output/index.js", "source_location": "L5", "weight": 1.0}, {"source": "index", "target": "store", "relation": "imports_from", "confidence": "EXTRACTED", "source_file": "node_modules/next/dist/esm/build/output/index.js", "source_location": "L6", "weight": 1.0}, {"source": "index", "target": "constants", "relation": "imports_from", "confidence": "EXTRACTED", "source_file": "node_modules/next/dist/esm/build/output/index.js", "source_location": "L7", "weight": 1.0}, {"source": "index", "target": "index_formatampmessages", "relation": "contains", "confidence": "EXTRACTED", "source_file": "node_modules/next/dist/esm/build/output/index.js", "source_location": "L8", "weight": 1.0}, {"source": "index", "target": "index_ampvalidation", "relation": "contains", "confidence": "EXTRACTED", "source_file": "node_modules/next/dist/esm/build/output/index.js", "source_location": "L144", "weight": 1.0}, {"source": "index", "target": "index_watchcompilers", "relation": "contains", "confidence": "EXTRACTED", "source_file": "node_modules/next/dist/esm/build/output/index.js", "source_location": "L165", "weight": 1.0}, {"source": "index", "target": "index_reporttrigger", "relation": "contains", "confidence": "EXTRACTED", "source_file": "node_modules/next/dist/esm/build/output/index.js", "source_location": "L243", "weight": 1.0}]}