{"nodes": [{"id": "culori_umd", "label": "culori.umd.js", "file_type": "code", "source_file": "node_modules/culori/bundled/culori.umd.js", "source_location": "L1"}, {"id": "culori_umd_is_num", "label": "is_num()", "file_type": "code", "source_file": "node_modules/culori/bundled/culori.umd.js", "source_location": "L631"}, {"id": "culori_umd_is_ident", "label": "is_ident()", "file_type": "code", "source_file": "node_modules/culori/bundled/culori.umd.js", "source_location": "L642"}, {"id": "culori_umd_num2", "label": "num2()", "file_type": "code", "source_file": "node_modules/culori/bundled/culori.umd.js", "source_location": "L668"}, {"id": "culori_umd_digits", "label": "digits()", "file_type": "code", "source_file": "node_modules/culori/bundled/culori.umd.js", "source_location": "L697"}, {"id": "culori_umd_ident", "label": "ident()", "file_type": "code", "source_file": "node_modules/culori/bundled/culori.umd.js", "source_location": "L704"}, {"id": "culori_umd_identlike", "label": "identlike()", "file_type": "code", "source_file": "node_modules/culori/bundled/culori.umd.js", "source_location": "L711"}, {"id": "culori_umd_tokenize", "label": "tokenize()", "file_type": "code", "source_file": "node_modules/culori/bundled/culori.umd.js", "source_location": "L722"}, {"id": "culori_umd_parsecolorsyntax", "label": "parseColorSyntax()", "file_type": "code", "source_file": "node_modules/culori/bundled/culori.umd.js", "source_location": "L807"}, {"id": "culori_umd_consumecoords", "label": "consumeCoords()", "file_type": "code", "source_file": "node_modules/culori/bundled/culori.umd.js", "source_location": "L839"}, {"id": "culori_umd_parsemodernsyntax", "label": "parseModernSyntax()", "file_type": "code", "source_file": "node_modules/culori/bundled/culori.umd.js", "source_location": "L870"}, {"id": "culori_umd_parsergb", "label": "parseRgb()", "file_type": "code", "source_file": "node_modules/culori/bundled/culori.umd.js", "source_location": "L902"}, {"id": "culori_umd_average", "label": "average()", "file_type": "code", "source_file": "node_modules/culori/bundled/culori.umd.js", "source_location": "L1409"}, {"id": "culori_umd_converthsitorgb", "label": "convertHsiToRgb()", "file_type": "code", "source_file": "node_modules/culori/bundled/culori.umd.js", "source_location": "L1698"}, {"id": "culori_umd_convertrgbtohsi", "label": "convertRgbToHsi()", "file_type": "code", "source_file": "node_modules/culori/bundled/culori.umd.js", "source_location": "L1756"}, {"id": "culori_umd_converthsltorgb", "label": "convertHslToRgb()", "file_type": "code", "source_file": "node_modules/culori/bundled/culori.umd.js", "source_location": "L1804"}, {"id": "culori_umd_convertrgbtohsl", "label": "convertRgbToHsl()", "file_type": "code", "source_file": "node_modules/culori/bundled/culori.umd.js", "source_location": "L1839"}, {"id": "culori_umd_parsehsl", "label": "parseHsl()", "file_type": "code", "source_file": "node_modules/culori/bundled/culori.umd.js", "source_location": "L1899"}, {"id": "culori_umd_converthsvtorgb", "label": "convertHsvToRgb()", "file_type": "code", "source_file": "node_modules/culori/bundled/culori.umd.js", "source_location": "L1968"}, {"id": "culori_umd_convertrgbtohsv", "label": "convertRgbToHsv()", "file_type": "code", "source_file": "node_modules/culori/bundled/culori.umd.js", "source_location": "L2002"}, {"id": "culori_umd_converthwbtorgb", "label": "convertHwbToRgb()", "file_type": "code", "source_file": "node_modules/culori/bundled/culori.umd.js", "source_location": "L2050"}, {"id": "culori_umd_convertrgbtohwb", "label": "convertRgbToHwb()", "file_type": "code", "source_file": "node_modules/culori/bundled/culori.umd.js", "source_location": "L2067"}, {"id": "culori_umd_parsehwb", "label": "ParseHwb()", "file_type": "code", "source_file": "node_modules/culori/bundled/culori.umd.js", "source_location": "L2083"}, {"id": "culori_umd_transferpqdecode", "label": "transferPqDecode()", "file_type": "code", "source_file": "node_modules/culori/bundled/culori.umd.js", "source_location": "L2160"}, {"id": "culori_umd_transferpqencode", "label": "transferPqEncode()", "file_type": "code", "source_file": "node_modules/culori/bundled/culori.umd.js", "source_location": "L2165"}, {"id": "culori_umd_parselab", "label": "parseLab()", "file_type": "code", "source_file": "node_modules/culori/bundled/culori.umd.js", "source_location": "L2531"}, {"id": "culori_umd_parselch", "label": "parseLch()", "file_type": "code", "source_file": "node_modules/culori/bundled/culori.umd.js", "source_location": "L2613"}, {"id": "culori_umd_toe", "label": "toe()", "file_type": "code", "source_file": "node_modules/culori/bundled/culori.umd.js", "source_location": "L2941"}, {"id": "culori_umd_toe_inv", "label": "toe_inv()", "file_type": "code", "source_file": "node_modules/culori/bundled/culori.umd.js", "source_location": "L2947"}, {"id": "culori_umd_compute_max_saturation", "label": "compute_max_saturation()", "file_type": "code", "source_file": "node_modules/culori/bundled/culori.umd.js", "source_location": "L2953"}, {"id": "culori_umd_find_cusp", "label": "find_cusp()", "file_type": "code", "source_file": "node_modules/culori/bundled/culori.umd.js", "source_location": "L3007"}, {"id": "culori_umd_find_gamut_intersection", "label": "find_gamut_intersection()", "file_type": "code", "source_file": "node_modules/culori/bundled/culori.umd.js", "source_location": "L3014"}, {"id": "culori_umd_get_st_max", "label": "get_ST_max()", "file_type": "code", "source_file": "node_modules/culori/bundled/culori.umd.js", "source_location": "L3071"}, {"id": "culori_umd_get_cs", "label": "get_Cs()", "file_type": "code", "source_file": "node_modules/culori/bundled/culori.umd.js", "source_location": "L3079"}, {"id": "culori_umd_convertoklabtookhsl", "label": "convertOklabToOkhsl()", "file_type": "code", "source_file": "node_modules/culori/bundled/culori.umd.js", "source_location": "L3100"}, {"id": "culori_umd_convertokhsltooklab", "label": "convertOkhslToOklab()", "file_type": "code", "source_file": "node_modules/culori/bundled/culori.umd.js", "source_location": "L3136"}, {"id": "culori_umd_convertoklabtookhsv", "label": "convertOklabToOkhsv()", "file_type": "code", "source_file": "node_modules/culori/bundled/culori.umd.js", "source_location": "L3188"}, {"id": "culori_umd_convertokhsvtooklab", "label": "convertOkhsvToOklab()", "file_type": "code", "source_file": "node_modules/culori/bundled/culori.umd.js", "source_location": "L3225"}, {"id": "culori_umd_parseoklab", "label": "parseOklab()", "file_type": "code", "source_file": "node_modules/culori/bundled/culori.umd.js", "source_location": "L3277"}, {"id": "culori_umd_parseoklch", "label": "parseOklch()", "file_type": "code", "source_file": "node_modules/culori/bundled/culori.umd.js", "source_location": "L3334"}, {"id": "culori_umd_displayable", "label": "displayable()", "file_type": "code", "source_file": "node_modules/culori/bundled/culori.umd.js", "source_location": "L4332"}, {"id": "culori_umd_ingamut", "label": "inGamut()", "file_type": "code", "source_file": "node_modules/culori/bundled/culori.umd.js", "source_location": "L4335"}, {"id": "culori_umd_clamprgb", "label": "clampRgb()", "file_type": "code", "source_file": "node_modules/culori/bundled/culori.umd.js", "source_location": "L4343"}, {"id": "culori_umd_clampgamut", "label": "clampGamut()", "file_type": "code", "source_file": "node_modules/culori/bundled/culori.umd.js", "source_location": "L4349"}, {"id": "culori_umd_clampchroma", "label": "clampChroma()", "file_type": "code", "source_file": "node_modules/culori/bundled/culori.umd.js", "source_location": "L4373"}, {"id": "culori_umd_togamut", "label": "toGamut()", "file_type": "code", "source_file": "node_modules/culori/bundled/culori.umd.js", "source_location": "L4402"}, {"id": "culori_umd_luminance", "label": "luminance()", "file_type": "code", "source_file": "node_modules/culori/bundled/culori.umd.js", "source_location": "L4993"}, {"id": "culori_umd_contrast", "label": "contrast()", "file_type": "code", "source_file": "node_modules/culori/bundled/culori.umd.js", "source_location": "L4997"}], "edges": [{"source": "culori_umd", "target": "culori_umd_is_num", "relation": "contains", "confidence": "EXTRACTED", "source_file": "node_modules/culori/bundled/culori.umd.js", "source_location": "L631", "weight": 1.0}, {"source": "culori_umd", "target": "culori_umd_is_ident", "relation": "contains", "confidence": "EXTRACTED", "source_file": "node_modules/culori/bundled/culori.umd.js", "source_location": "L642", "weight": 1.0}, {"source": "culori_umd", "target": "culori_umd_num2", "relation": "contains", "confidence": "EXTRACTED", "source_file": "node_modules/culori/bundled/culori.umd.js", "source_location": "L668", "weight": 1.0}, {"source": "culori_umd", "target": "culori_umd_digits", "relation": "contains", "confidence": "EXTRACTED", "source_file": "node_modules/culori/bundled/culori.umd.js", "source_location": "L697", "weight": 1.0}, {"source": "culori_umd", "target": "culori_umd_ident", "relation": "contains", "confidence": "EXTRACTED", "source_file": "node_modules/culori/bundled/culori.umd.js", "source_location": "L704", "weight": 1.0}, {"source": "culori_umd", "target": "culori_umd_identlike", "relation": "contains", "confidence": "EXTRACTED", "source_file": "node_modules/culori/bundled/culori.umd.js", "source_location": "L711", "weight": 1.0}, {"source": "culori_umd", "target": "culori_umd_tokenize", "relation": "contains", "confidence": "EXTRACTED", "source_file": "node_modules/culori/bundled/culori.umd.js", "source_location": "L722", "weight": 1.0}, {"source": "culori_umd", "target": "culori_umd_parsecolorsyntax", "relation": "contains", "confidence": "EXTRACTED", "source_file": "node_modules/culori/bundled/culori.umd.js", "source_location": "L807", "weight": 1.0}, {"source": "culori_umd", "target": "culori_umd_consumecoords", "relation": "contains", "confidence": "EXTRACTED", "source_file": "node_modules/culori/bundled/culori.umd.js", "source_location": "L839", "weight": 1.0}, {"source": "culori_umd", "target": "culori_umd_parsemodernsyntax", "relation": "contains", "confidence": "EXTRACTED", "source_file": "node_modules/culori/bundled/culori.umd.js", "source_location": "L870", "weight": 1.0}, {"source": "culori_umd", "target": "culori_umd_parsergb", "relation": "contains", "confidence": "EXTRACTED", "source_file": "node_modules/culori/bundled/culori.umd.js", "source_location": "L902", "weight": 1.0}, {"source": "culori_umd", "target": "culori_umd_average", "relation": "contains", "confidence": "EXTRACTED", "source_file": "node_modules/culori/bundled/culori.umd.js", "source_location": "L1409", "weight": 1.0}, {"source": "culori_umd", "target": "culori_umd_converthsitorgb", "relation": "contains", "confidence": "EXTRACTED", "source_file": "node_modules/culori/bundled/culori.umd.js", "source_location": "L1698", "weight": 1.0}, {"source": "culori_umd", "target": "culori_umd_convertrgbtohsi", "relation": "contains", "confidence": "EXTRACTED", "source_file": "node_modules/culori/bundled/culori.umd.js", "source_location": "L1756", "weight": 1.0}, {"source": "culori_umd", "target": "culori_umd_converthsltorgb", "relation": "contains", "confidence": "EXTRACTED", "source_file": "node_modules/culori/bundled/culori.umd.js", "source_location": "L1804", "weight": 1.0}, {"source": "culori_umd", "target": "culori_umd_convertrgbtohsl", "relation": "contains", "confidence": "EXTRACTED", "source_file": "node_modules/culori/bundled/culori.umd.js", "source_location": "L1839", "weight": 1.0}, {"source": "culori_umd", "target": "culori_umd_parsehsl", "relation": "contains", "confidence": "EXTRACTED", "source_file": "node_modules/culori/bundled/culori.umd.js", "source_location": "L1899", "weight": 1.0}, {"source": "culori_umd", "target": "culori_umd_converthsvtorgb", "relation": "contains", "confidence": "EXTRACTED", "source_file": "node_modules/culori/bundled/culori.umd.js", "source_location": "L1968", "weight": 1.0}, {"source": "culori_umd", "target": "culori_umd_convertrgbtohsv", "relation": "contains", "confidence": "EXTRACTED", "source_file": "node_modules/culori/bundled/culori.umd.js", "source_location": "L2002", "weight": 1.0}, {"source": "culori_umd", "target": "culori_umd_converthwbtorgb", "relation": "contains", "confidence": "EXTRACTED", "source_file": "node_modules/culori/bundled/culori.umd.js", "source_location": "L2050", "weight": 1.0}, {"source": "culori_umd", "target": "culori_umd_convertrgbtohwb", "relation": "contains", "confidence": "EXTRACTED", "source_file": "node_modules/culori/bundled/culori.umd.js", "source_location": "L2067", "weight": 1.0}, {"source": "culori_umd", "target": "culori_umd_parsehwb", "relation": "contains", "confidence": "EXTRACTED", "source_file": "node_modules/culori/bundled/culori.umd.js", "source_location": "L2083", "weight": 1.0}, {"source": "culori_umd", "target": "culori_umd_transferpqdecode", "relation": "contains", "confidence": "EXTRACTED", "source_file": "node_modules/culori/bundled/culori.umd.js", "source_location": "L2160", "weight": 1.0}, {"source": "culori_umd", "target": "culori_umd_transferpqencode", "relation": "contains", "confidence": "EXTRACTED", "source_file": "node_modules/culori/bundled/culori.umd.js", "source_location": "L2165", "weight": 1.0}, {"source": "culori_umd", "target": "culori_umd_parselab", "relation": "contains", "confidence": "EXTRACTED", "source_file": "node_modules/culori/bundled/culori.umd.js", "source_location": "L2531", "weight": 1.0}, {"source": "culori_umd", "target": "culori_umd_parselch", "relation": "contains", "confidence": "EXTRACTED", "source_file": "node_modules/culori/bundled/culori.umd.js", "source_location": "L2613", "weight": 1.0}, {"source": "culori_umd", "target": "culori_umd_toe", "relation": "contains", "confidence": "EXTRACTED", "source_file": "node_modules/culori/bundled/culori.umd.js", "source_location": "L2941", "weight": 1.0}, {"source": "culori_umd", "target": "culori_umd_toe_inv", "relation": "contains", "confidence": "EXTRACTED", "source_file": "node_modules/culori/bundled/culori.umd.js", "source_location": "L2947", "weight": 1.0}, {"source": "culori_umd", "target": "culori_umd_compute_max_saturation", "relation": "contains", "confidence": "EXTRACTED", "source_file": "node_modules/culori/bundled/culori.umd.js", "source_location": "L2953", "weight": 1.0}, {"source": "culori_umd", "target": "culori_umd_find_cusp", "relation": "contains", "confidence": "EXTRACTED", "source_file": "node_modules/culori/bundled/culori.umd.js", "source_location": "L3007", "weight": 1.0}, {"source": "culori_umd", "target": "culori_umd_find_gamut_intersection", "relation": "contains", "confidence": "EXTRACTED", "source_file": "node_modules/culori/bundled/culori.umd.js", "source_location": "L3014", "weight": 1.0}, {"source": "culori_umd", "target": "culori_umd_get_st_max", "relation": "contains", "confidence": "EXTRACTED", "source_file": "node_modules/culori/bundled/culori.umd.js", "source_location": "L3071", "weight": 1.0}, {"source": "culori_umd", "target": "culori_umd_get_cs", "relation": "contains", "confidence": "EXTRACTED", "source_file": "node_modules/culori/bundled/culori.umd.js", "source_location": "L3079", "weight": 1.0}, {"source": "culori_umd", "target": "culori_umd_convertoklabtookhsl", "relation": "contains", "confidence": "EXTRACTED", "source_file": "node_modules/culori/bundled/culori.umd.js", "source_location": "L3100", "weight": 1.0}, {"source": "culori_umd", "target": "culori_umd_convertokhsltooklab", "relation": "contains", "confidence": "EXTRACTED", "source_file": "node_modules/culori/bundled/culori.umd.js", "source_location": "L3136", "weight": 1.0}, {"source": "culori_umd", "target": "culori_umd_convertoklabtookhsv", "relation": "contains", "confidence": "EXTRACTED", "source_file": "node_modules/culori/bundled/culori.umd.js", "source_location": "L3188", "weight": 1.0}, {"source": "culori_umd", "target": "culori_umd_convertokhsvtooklab", "relation": "contains", "confidence": "EXTRACTED", "source_file": "node_modules/culori/bundled/culori.umd.js", "source_location": "L3225", "weight": 1.0}, {"source": "culori_umd", "target": "culori_umd_parseoklab", "relation": "contains", "confidence": "EXTRACTED", "source_file": "node_modules/culori/bundled/culori.umd.js", "source_location": "L3277", "weight": 1.0}, {"source": "culori_umd", "target": "culori_umd_parseoklch", "relation": "contains", "confidence": "EXTRACTED", "source_file": "node_modules/culori/bundled/culori.umd.js", "source_location": "L3334", "weight": 1.0}, {"source": "culori_umd", "target": "culori_umd_displayable", "relation": "contains", "confidence": "EXTRACTED", "source_file": "node_modules/culori/bundled/culori.umd.js", "source_location": "L4332", "weight": 1.0}, {"source": "culori_umd", "target": "culori_umd_ingamut", "relation": "contains", "confidence": "EXTRACTED", "source_file": "node_modules/culori/bundled/culori.umd.js", "source_location": "L4335", "weight": 1.0}, {"source": "culori_umd", "target": "culori_umd_clamprgb", "relation": "contains", "confidence": "EXTRACTED", "source_file": "node_modules/culori/bundled/culori.umd.js", "source_location": "L4343", "weight": 1.0}, {"source": "culori_umd", "target": "culori_umd_clampgamut", "relation": "contains", "confidence": "EXTRACTED", "source_file": "node_modules/culori/bundled/culori.umd.js", "source_location": "L4349", "weight": 1.0}, {"source": "culori_umd", "target": "culori_umd_clampchroma", "relation": "contains", "confidence": "EXTRACTED", "source_file": "node_modules/culori/bundled/culori.umd.js", "source_location": "L4373", "weight": 1.0}, {"source": "culori_umd", "target": "culori_umd_togamut", "relation": "contains", "confidence": "EXTRACTED", "source_file": "node_modules/culori/bundled/culori.umd.js", "source_location": "L4402", "weight": 1.0}, {"source": "culori_umd", "target": "culori_umd_luminance", "relation": "contains", "confidence": "EXTRACTED", "source_file": "node_modules/culori/bundled/culori.umd.js", "source_location": "L4993", "weight": 1.0}, {"source": "culori_umd", "target": "culori_umd_contrast", "relation": "contains", "confidence": "EXTRACTED", "source_file": "node_modules/culori/bundled/culori.umd.js", "source_location": "L4997", "weight": 1.0}, {"source": "culori_umd_num2", "target": "culori_umd_digits", "relation": "calls", "confidence": "INFERRED", "source_file": "node_modules/culori/bundled/culori.umd.js", "source_location": "L673", "weight": 0.8}, {"source": "culori_umd_num2", "target": "culori_umd_is_ident", "relation": "calls", "confidence": "INFERRED", "source_file": "node_modules/culori/bundled/culori.umd.js", "source_location": "L684", "weight": 0.8}, {"source": "culori_umd_num2", "target": "culori_umd_ident", "relation": "calls", "confidence": "INFERRED", "source_file": "node_modules/culori/bundled/culori.umd.js", "source_location": "L685", "weight": 0.8}, {"source": "culori_umd_identlike", "target": "culori_umd_ident", "relation": "calls", "confidence": "INFERRED", "source_file": "node_modules/culori/bundled/culori.umd.js", "source_location": "L712", "weight": 0.8}, {"source": "culori_umd_tokenize", "target": "culori_umd_is_num", "relation": "calls", "confidence": "INFERRED", "source_file": "node_modules/culori/bundled/culori.umd.js", "source_location": "L744", "weight": 0.8}, {"source": "culori_umd_tokenize", "target": "culori_umd_num2", "relation": "calls", "confidence": "INFERRED", "source_file": "node_modules/culori/bundled/culori.umd.js", "source_location": "L745", "weight": 0.8}, {"source": "culori_umd_tokenize", "target": "culori_umd_is_ident", "relation": "calls", "confidence": "INFERRED", "source_file": "node_modules/culori/bundled/culori.umd.js", "source_location": "L756", "weight": 0.8}, {"source": "culori_umd_tokenize", "target": "culori_umd_ident", "relation": "calls", "confidence": "INFERRED", "source_file": "node_modules/culori/bundled/culori.umd.js", "source_location": "L757", "weight": 0.8}, {"source": "culori_umd_tokenize", "target": "culori_umd_identlike", "relation": "calls", "confidence": "INFERRED", "source_file": "node_modules/culori/bundled/culori.umd.js", "source_location": "L800", "weight": 0.8}, {"source": "culori_umd_parsecolorsyntax", "target": "culori_umd_consumecoords", "relation": "calls", "confidence": "INFERRED", "source_file": "node_modules/culori/bundled/culori.umd.js", "source_location": "L822", "weight": 0.8}, {"source": "culori_umd_parsemodernsyntax", "target": "culori_umd_consumecoords", "relation": "calls", "confidence": "INFERRED", "source_file": "node_modules/culori/bundled/culori.umd.js", "source_location": "L876", "weight": 0.8}, {"source": "culori_umd_converthwbtorgb", "target": "culori_umd_converthsvtorgb", "relation": "calls", "confidence": "INFERRED", "source_file": "node_modules/culori/bundled/culori.umd.js", "source_location": "L2058", "weight": 0.8}, {"source": "culori_umd_convertrgbtohwb", "target": "culori_umd_convertrgbtohsv", "relation": "calls", "confidence": "INFERRED", "source_file": "node_modules/culori/bundled/culori.umd.js", "source_location": "L2068", "weight": 0.8}, {"source": "culori_umd_find_cusp", "target": "culori_umd_compute_max_saturation", "relation": "calls", "confidence": "INFERRED", "source_file": "node_modules/culori/bundled/culori.umd.js", "source_location": "L3008", "weight": 0.8}, {"source": "culori_umd_find_gamut_intersection", "target": "culori_umd_find_cusp", "relation": "calls", "confidence": "INFERRED", "source_file": "node_modules/culori/bundled/culori.umd.js", "source_location": "L3016", "weight": 0.8}, {"source": "culori_umd_get_st_max", "target": "culori_umd_find_cusp", "relation": "calls", "confidence": "INFERRED", "source_file": "node_modules/culori/bundled/culori.umd.js", "source_location": "L3073", "weight": 0.8}, {"source": "culori_umd_get_cs", "target": "culori_umd_find_cusp", "relation": "calls", "confidence": "INFERRED", "source_file": "node_modules/culori/bundled/culori.umd.js", "source_location": "L3080", "weight": 0.8}, {"source": "culori_umd_get_cs", "target": "culori_umd_find_gamut_intersection", "relation": "calls", "confidence": "INFERRED", "source_file": "node_modules/culori/bundled/culori.umd.js", "source_location": "L3081", "weight": 0.8}, {"source": "culori_umd_get_cs", "target": "culori_umd_get_st_max", "relation": "calls", "confidence": "INFERRED", "source_file": "node_modules/culori/bundled/culori.umd.js", "source_location": "L3082", "weight": 0.8}, {"source": "culori_umd_convertoklabtookhsl", "target": "culori_umd_toe", "relation": "calls", "confidence": "INFERRED", "source_file": "node_modules/culori/bundled/culori.umd.js", "source_location": "L3104", "weight": 0.8}, {"source": "culori_umd_convertoklabtookhsl", "target": "culori_umd_get_cs", "relation": "calls", "confidence": "INFERRED", "source_file": "node_modules/culori/bundled/culori.umd.js", "source_location": "L3113", "weight": 0.8}, {"source": "culori_umd_convertokhsltooklab", "target": "culori_umd_toe_inv", "relation": "calls", "confidence": "INFERRED", "source_file": "node_modules/culori/bundled/culori.umd.js", "source_location": "L3140", "weight": 0.8}, {"source": "culori_umd_convertokhsltooklab", "target": "culori_umd_get_cs", "relation": "calls", "confidence": "INFERRED", "source_file": "node_modules/culori/bundled/culori.umd.js", "source_location": "L3150", "weight": 0.8}, {"source": "culori_umd_convertoklabtookhsv", "target": "culori_umd_get_st_max", "relation": "calls", "confidence": "INFERRED", "source_file": "node_modules/culori/bundled/culori.umd.js", "source_location": "L3195", "weight": 0.8}, {"source": "culori_umd_convertoklabtookhsv", "target": "culori_umd_toe_inv", "relation": "calls", "confidence": "INFERRED", "source_file": "node_modules/culori/bundled/culori.umd.js", "source_location": "L3201", "weight": 0.8}, {"source": "culori_umd_convertoklabtookhsv", "target": "culori_umd_toe", "relation": "calls", "confidence": "INFERRED", "source_file": "node_modules/culori/bundled/culori.umd.js", "source_location": "L3208", "weight": 0.8}, {"source": "culori_umd_convertokhsvtooklab", "target": "culori_umd_get_st_max", "relation": "calls", "confidence": "INFERRED", "source_file": "node_modules/culori/bundled/culori.umd.js", "source_location": "L3235", "weight": 0.8}, {"source": "culori_umd_convertokhsvtooklab", "target": "culori_umd_toe_inv", "relation": "calls", "confidence": "INFERRED", "source_file": "node_modules/culori/bundled/culori.umd.js", "source_location": "L3240", "weight": 0.8}, {"source": "culori_umd_clamprgb", "target": "culori_umd_displayable", "relation": "calls", "confidence": "INFERRED", "source_file": "node_modules/culori/bundled/culori.umd.js", "source_location": "L4345", "weight": 0.8}, {"source": "culori_umd_clampgamut", "target": "culori_umd_ingamut", "relation": "calls", "confidence": "INFERRED", "source_file": "node_modules/culori/bundled/culori.umd.js", "source_location": "L4356", "weight": 0.8}, {"source": "culori_umd_clampchroma", "target": "culori_umd_ingamut", "relation": "calls", "confidence": "INFERRED", "source_file": "node_modules/culori/bundled/culori.umd.js", "source_location": "L4375", "weight": 0.8}, {"source": "culori_umd_clampchroma", "target": "culori_umd_clampgamut", "relation": "calls", "confidence": "INFERRED", "source_file": "node_modules/culori/bundled/culori.umd.js", "source_location": "L4376", "weight": 0.8}, {"source": "culori_umd_togamut", "target": "culori_umd_ingamut", "relation": "calls", "confidence": "INFERRED", "source_file": "node_modules/culori/bundled/culori.umd.js", "source_location": "L4408", "weight": 0.8}, {"source": "culori_umd_togamut", "target": "culori_umd_clampgamut", "relation": "calls", "confidence": "INFERRED", "source_file": "node_modules/culori/bundled/culori.umd.js", "source_location": "L4409", "weight": 0.8}, {"source": "culori_umd_contrast", "target": "culori_umd_luminance", "relation": "calls", "confidence": "INFERRED", "source_file": "node_modules/culori/bundled/culori.umd.js", "source_location": "L4998", "weight": 0.8}]}