{"nodes": [{"id": "convertrgbtoxyz50", "label": "convertRgbToXyz50.js", "file_type": "code", "source_file": "node_modules/culori/src/xyz50/convertRgbToXyz50.js", "source_location": "L1"}, {"id": "convertrgbtoxyz50_convertrgbtoxyz50", "label": "convertRgbToXyz50()", "file_type": "code", "source_file": "node_modules/culori/src/xyz50/convertRgbToXyz50.js", "source_location": "L12"}], "edges": [{"source": "convertrgbtoxyz50", "target": "convertrgbtolrgb_js", "relation": "imports_from", "confidence": "EXTRACTED", "source_file": "node_modules/culori/src/xyz50/convertRgbToXyz50.js", "source_location": "L10", "weight": 1.0}, {"source": "convertrgbtoxyz50", "target": "convertrgbtoxyz50_convertrgbtoxyz50", "relation": "contains", "confidence": "EXTRACTED", "source_file": "node_modules/culori/src/xyz50/convertRgbToXyz50.js", "source_location": "L12", "weight": 1.0}]}