{"nodes": [{"id": "convertxyz65toa98", "label": "convertXyz65ToA98.js", "file_type": "code", "source_file": "node_modules/culori/src/a98/convertXyz65ToA98.js", "source_location": "L1"}, {"id": "convertxyz65toa98_gamma", "label": "gamma()", "file_type": "code", "source_file": "node_modules/culori/src/a98/convertXyz65ToA98.js", "source_location": "L9"}, {"id": "convertxyz65toa98_convertxyz65toa98", "label": "convertXyz65ToA98()", "file_type": "code", "source_file": "node_modules/culori/src/a98/convertXyz65ToA98.js", "source_location": "L11"}], "edges": [{"source": "convertxyz65toa98", "target": "convertxyz65toa98_gamma", "relation": "contains", "confidence": "EXTRACTED", "source_file": "node_modules/culori/src/a98/convertXyz65ToA98.js", "source_location": "L9", "weight": 1.0}, {"source": "convertxyz65toa98", "target": "convertxyz65toa98_convertxyz65toa98", "relation": "contains", "confidence": "EXTRACTED", "source_file": "node_modules/culori/src/a98/convertXyz65ToA98.js", "source_location": "L11", "weight": 1.0}, {"source": "convertxyz65toa98_convertxyz65toa98", "target": "convertxyz65toa98_gamma", "relation": "calls", "confidence": "INFERRED", "source_file": "node_modules/culori/src/a98/convertXyz65ToA98.js", "source_location": "L17", "weight": 0.8}]}